setup.py
KleinSpace/Asteroid.py
KleinSpace/AsteroidBelt.py
KleinSpace/Bullet.py
KleinSpace/Menu.py
KleinSpace/__init__.py
KleinSpace/main.py
KleinSpace/spaceship.py
KleinSpace.egg-info/.DS_Store
KleinSpace.egg-info/PKG-INFO
KleinSpace.egg-info/SOURCES.txt
KleinSpace.egg-info/dependency_links.txt
KleinSpace.egg-info/not-zip-safe
KleinSpace.egg-info/top_level.txt