Metadata-Version: 1.0
Name: KleinSpace
Version: 0.1
Summary: Klein Space
Home-page: UNKNOWN
Author: Klein Space Fighter
Author-email: HaleyoBourke@yahoo.com
License: UNKNOWN
Platform: UNKNOWN
